<?xml version="1.0" encoding="utf-8"?>
<!DOCTYPE hibernate-mapping PUBLIC "-//Hibernate/Hibernate Mapping DTD 3.0//EN"
"http://www.hibernate.org/dtd/hibernate-mapping-3.0.dtd">
<!-- 
    Mapping file autogenerated by MyEclipse Persistence Tools
-->
<hibernate-mapping>
    <class name="edu.iasd.pojo.County" table="t_county" catalog="tsjyw" >
        <id name="countyId" type="java.lang.Integer">
            <column name="CountyId" />
            <generator class="increment"></generator>
        </id>
        <property name="countyName" type="java.lang.String">
            <column name="CountyName" length="50" not-null="true" />
        </property>  
        <set name="countyManagers" inverse="true">
            <key>
                <column name="CountyId" not-null="true" />
            </key>
            <one-to-many class="edu.iasd.pojo.CountyManager" />
        </set>
        
        
        <set name="schools" inverse="true">
            <key>
                <column name="CountyId" not-null="true" />
            </key>
            <one-to-many class="edu.iasd.pojo.School" />
        </set>
    </class>
</hibernate-mapping>
